shared_lovelike/__init__.py
shared_lovelike/entities.py
shared_lovelike/common/__init__.py
shared_lovelike/common/unix_timestamp.py
shared_lovelike/database/__init__.py
shared_lovelike/database/base.py
shared_lovelike/database/session.py
shared_lovelike-0.1.1.dist-info/METADATA
shared_lovelike-0.1.1.dist-info/WHEEL
shared_lovelike-0.1.1.dist-info/top_level.txt
shared_lovelike-0.1.1.dist-info/RECORD
