Metadata-Version: 2.2
Name: shared_lovelike
Version: 0.1.1
Summary: Pacote responsavel por compartilhar as entidades do projeto LoveLike
Author: George Augusto da Silva
Author-email: ge_silva1991@hotmail.com
Requires-Dist: fastapi>=0.115.8
Requires-Dist: SQLAlchemy>=2.0.37
Requires-Dist: psycopg2>=2.9.10
Requires-Dist: alembic>=1.14.1
Dynamic: author
Dynamic: author-email
Dynamic: requires-dist
Dynamic: summary
